christo8/__init__.py
christo8/christo8.py
christo8-0.1.dist-info/LICENSE.txt
christo8-0.1.dist-info/METADATA
christo8-0.1.dist-info/WHEEL
christo8-0.1.dist-info/top_level.txt
christo8-0.1.dist-info/RECORD
